deepgram_cli/__init__.py
deepgram_cli/app.py
deepgram_cli/cli.py
deepgram_cli/constants.py
deepgram_cli/deepgram_cli.py
deepgram_cli/utils.py
deepgram_cli/version.py
deepgram_cli-0.0.2.dist-info/LICENSE
deepgram_cli-0.0.2.dist-info/METADATA
deepgram_cli-0.0.2.dist-info/WHEEL
deepgram_cli-0.0.2.dist-info/entry_points.txt
deepgram_cli-0.0.2.dist-info/top_level.txt
deepgram_cli-0.0.2.dist-info/RECORD
