Metadata-Version: 2.1
Name: deepgram-cli
Version: 0.0.2
Summary: deepgram cli for bulk transcribing files.
Home-page: https://github.com/skyme5/deepgram-cli
Author: Aakash Gajjar
Author-email: skyqutip@gmail.com
License: MIT license
Keywords: deepgram-cli
Platform: UNKNOWN
Classifier: Development Status :: 5 - Production/Stable
Classifier: Environment :: Console
Classifier: Intended Audience :: Developers
Classifier: Intended Audience :: End Users/Desktop
Classifier: License :: OSI Approved :: MIT License
Classifier: Natural Language :: English
Classifier: Programming Language :: Python :: 3
Requires-Python: >=3.5
License-File: LICENSE
Requires-Dist: deepgram-sdk
Requires-Dist: requests
